django_app_metadata/.DS_Store
django_app_metadata/__init__.py
django_app_metadata/admin.py
django_app_metadata/apps.py
django_app_metadata/exceptions.py
django_app_metadata/models.py
django_app_metadata/settings.py
django_app_metadata/tests.py
django_app_metadata/version.py
django_app_metadata/views.py
django_app_metadata/locale/zh_Hans/LC_MESSAGES/django.po
django_app_metadata/migrations/0001_initial.py
django_app_metadata/migrations/0002_alter_config_key.py
django_app_metadata/migrations/0003_alter_config_options_config_data_file_and_more.py
django_app_metadata/migrations/__init__.py
django_app_metadata-0.1.4.dist-info/licenses/LICENSE
django_app_metadata-0.1.4.dist-info/METADATA
django_app_metadata-0.1.4.dist-info/WHEEL
django_app_metadata-0.1.4.dist-info/top_level.txt
django_app_metadata-0.1.4.dist-info/RECORD
